odoo/addons/document_page_tag_print_control/README.rst
odoo/addons/document_page_tag_print_control/__init__.py
odoo/addons/document_page_tag_print_control/__manifest__.py
odoo/addons/document_page_tag_print_control/i18n/ca_ES.po
odoo/addons/document_page_tag_print_control/i18n/document_page_tag_print_control.pot
odoo/addons/document_page_tag_print_control/i18n/es.po
odoo/addons/document_page_tag_print_control/i18n/it.po
odoo/addons/document_page_tag_print_control/models/__init__.py
odoo/addons/document_page_tag_print_control/models/document_page.py
odoo/addons/document_page_tag_print_control/models/document_page_tag.py
odoo/addons/document_page_tag_print_control/models/report_document_page.py
odoo/addons/document_page_tag_print_control/readme/CONTRIBUTORS.md
odoo/addons/document_page_tag_print_control/readme/DESCRIPTION.md
odoo/addons/document_page_tag_print_control/readme/USAGE.md
odoo/addons/document_page_tag_print_control/static/description/icon.png
odoo/addons/document_page_tag_print_control/static/description/index.html
odoo/addons/document_page_tag_print_control/tests/__init__.py
odoo/addons/document_page_tag_print_control/tests/test_document_page_tag_print_control.py
odoo/addons/document_page_tag_print_control/views/document_page_tag.xml
odoo_addon_document_page_tag_print_control-17.0.1.0.0.3.dist-info/METADATA
odoo_addon_document_page_tag_print_control-17.0.1.0.0.3.dist-info/WHEEL
odoo_addon_document_page_tag_print_control-17.0.1.0.0.3.dist-info/top_level.txt
odoo_addon_document_page_tag_print_control-17.0.1.0.0.3.dist-info/RECORD
